qina-1.0.7.dist-info/licenses/LICENSE
qina_security_editor/__init__.py
qina_security_editor/auth_service.py
qina_security_editor/chat_service.py
qina_security_editor/config_manager.py
qina_security_editor/f.py
qina_security_editor/findings_manager.py
qina_security_editor/js_scan_service.py
qina_security_editor/main.py
qina_security_editor/sarif_parser.py
qina_security_editor/scan_result_parser.py
qina_security_editor/try.py
qina-1.0.7.dist-info/METADATA
qina-1.0.7.dist-info/WHEEL
qina-1.0.7.dist-info/entry_points.txt
qina-1.0.7.dist-info/top_level.txt
qina-1.0.7.dist-info/RECORD
