Metadata-Version: 2.4
Name: qina
Version: 1.0.7
Summary: A code monitoring and vulnerability scanning terminal application
Author-email: CloudDefense AI <support@clouddefenseai.com>
Maintainer-email: CloudDefense AI <support@clouddefenseai.com>
License: MIT
Project-URL: Homepage, https://github.com/clouddefenseai/qina
Project-URL: Documentation, https://github.com/clouddefenseai/qina#readme
Project-URL: Repository, https://github.com/clouddefenseai/qina
Project-URL: Bug Tracker, https://github.com/clouddefenseai/qina/issues
Keywords: security,vulnerability,scanning,code-analysis,devsecops
Classifier: Development Status :: 4 - Beta
Classifier: Intended Audience :: Developers
Classifier: Topic :: Software Development :: Quality Assurance
Classifier: Topic :: Security
Classifier: License :: OSI Approved :: MIT License
Classifier: Programming Language :: Python :: 3
Classifier: Programming Language :: Python :: 3.8
Classifier: Programming Language :: Python :: 3.9
Classifier: Programming Language :: Python :: 3.10
Classifier: Programming Language :: Python :: 3.11
Classifier: Programming Language :: Python :: 3.12
Requires-Python: >=3.8
License-File: LICENSE
Requires-Dist: aiohappyeyeballs==2.6.1
Requires-Dist: aiohttp==3.13.0
Requires-Dist: aiosignal==1.4.0
Requires-Dist: attrs==25.4.0
Requires-Dist: certifi==2025.10.5
Requires-Dist: charset-normalizer==3.4.4
Requires-Dist: colorama==0.4.6
Requires-Dist: frozenlist==1.8.0
Requires-Dist: idna==3.11
Requires-Dist: multidict==6.7.0
Requires-Dist: propcache==0.4.1
Requires-Dist: requests==2.32.5
Requires-Dist: typing_extensions==4.15.0
Requires-Dist: urllib3==2.5.0
Requires-Dist: watchdog==6.0.0
Requires-Dist: websockets==15.0.1
Requires-Dist: yarl==1.22.0
Provides-Extra: dev
Requires-Dist: pytest>=6.0; extra == "dev"
Requires-Dist: pytest-cov; extra == "dev"
Requires-Dist: black; extra == "dev"
Requires-Dist: flake8; extra == "dev"
Requires-Dist: mypy; extra == "dev"
Dynamic: license-file
